clip/GTxFeature.py
clip/Gene.py
clip/GeneLengthSummary.py
clip/GeneRegion.py
clip/__init__.py
clip/bamCLIP.py
clip/bedCLIP.py
clip/clip.py
clip/command_line.py
clip/countCLIP.py
clip/createMatrix.py
clip/gffCLIP.py
clip/output.py
clip/trimAnnotation.py
htseq_clip-2.19.0b0.dist-info/LICENSE
htseq_clip-2.19.0b0.dist-info/METADATA
htseq_clip-2.19.0b0.dist-info/WHEEL
htseq_clip-2.19.0b0.dist-info/entry_points.txt
htseq_clip-2.19.0b0.dist-info/top_level.txt
htseq_clip-2.19.0b0.dist-info/RECORD
