Metadata-Version: 2.1
Name: htseq-clip
Version: 2.19.0b0
Summary: htseq-clip: a toolset for the analysis of eCLIP/iCLIP datasets
Home-page: https://github.com/EMBL-Hentze-group/htseq-clip
Author: Thomas Schwarzl, Sudeep Sahadevan, Marko Fritz, Nadia Ashraf
Author-email: schwarzl@embl.de, sudeep.sahadevan@embl.de
License: MIT
Classifier: Development Status :: 4 - Beta
Classifier: Intended Audience :: Science/Research
Classifier: Topic :: Scientific/Engineering :: Bio-Informatics
Classifier: License :: OSI Approved :: MIT License
Classifier: Environment :: Console
Classifier: Natural Language :: English
Classifier: Programming Language :: Python :: 3
License-File: LICENSE
Requires-Dist: HTSeq
Requires-Dist: pysam
